Metadata-Version: 2.2
Name: MateLibre
Version: 0.1
Summary: Librería matemática con operaciones básicas y álgebra
Home-page: https://github.com/tuusuario/matelibre
Author: Tu Nombre
Classifier: Programming Language :: Python :: 3
Classifier: License :: OSI Approved :: MIT License
Classifier: Operating System :: OS Independent
Dynamic: author
Dynamic: classifier
Dynamic: home-page
Dynamic: summary
